LICENSE
MANIFEST.in
NAME
README.md
VERSION
setup.py
rmq_engine/__init__.py
rmq_engine/rabbitmq.py
rmq_engine/rmq_engine.py
tests/rabbitmq_read.py