Metadata-Version: 2.1
Name: rmq_engine
Version: 0.0.4
Summary: Engine class for AMQP collect data froma a queue
Home-page: http://gitlab.csn.uchile.cl/dpineda/rmq_engine
Author: David Pineda Osorio
Author-email: dpineda@csn.uchile.cl
License: MIT
Keywords: amqp,data,broker,async
Platform: UNKNOWN
